ahrens_lab_to_nwb/__init__.py
ahrens_lab_to_nwb/yu_mu_cell_2019/__init__.py
ahrens_lab_to_nwb/yu_mu_cell_2019/yu_mu_cell_2019_conversion_script_dual_color.py
ahrens_lab_to_nwb/yu_mu_cell_2019/yu_mu_cell_2019_conversion_script_single_color.py
ahrens_lab_to_nwb/yu_mu_cell_2019/yu_mu_cell_2019_nwbconverter.py
ahrens_lab_to_nwb-1.0.0.dist-info/LICENSE
ahrens_lab_to_nwb-1.0.0.dist-info/METADATA
ahrens_lab_to_nwb-1.0.0.dist-info/WHEEL
ahrens_lab_to_nwb-1.0.0.dist-info/top_level.txt
ahrens_lab_to_nwb-1.0.0.dist-info/RECORD
