Metadata-Version: 2.1
Name: ahrens-lab-to-nwb
Version: 1.0.0
Summary: NWB conversion scripts, functions, and classes for an the Ahrens lab.
Home-page: https://github.com/catalystneuro/ahrens-lab-to-nwb
Author: CatalystNeuro
License: UNKNOWN
Platform: UNKNOWN
Requires-Python: >=3.7
Requires-Dist: neuroconv
Requires-Dist: nwbwidgets
Provides-Extra: yu_mu_cell_2019
Requires-Dist: ndx-events (==0.2.0) ; extra == 'yu_mu_cell_2019'
